<?xml version="1.0" encoding="UTF-8"?>
<mxGraphModel dx="1176" dy="562" grid="1" gridSize="10" guides="1" tooltips="1" connect="1" fold="0" page="1" pageScale="1" pageWidth="1169" pageHeight="826" style="default-style2" math="0"><root><mxCell id="4c01e10969289608-0"/><mxCell id="4c01e10969289608-1" parent="4c01e10969289608-0"/><mxCell id="10abfec4e11a1f11-5" value="Codelist" style="html=1;" vertex="1" parent="4c01e10969289608-1"><mxGeometry x="240" y="198" width="80" height="25" as="geometry"/></mxCell><mxCell id="10abfec4e11a1f11-7" value="CodelistClass" style="html=1;" vertex="1" parent="4c01e10969289608-1"><mxGeometry x="555" y="198" width="90" height="25" as="geometry"/></mxCell><mxCell id="10abfec4e11a1f11-12" value="Concept" style="html=1;" vertex="1" parent="4c01e10969289608-1"><mxGeometry x="560" y="310" width="80" height="25" as="geometry"/></mxCell><mxCell id="10abfec4e11a1f11-13" value="skos:Concept" style="html=1;" vertex="1" parent="4c01e10969289608-1"><mxGeometry x="775" y="310" width="90" height="25" as="geometry"/></mxCell><mxCell id="10abfec4e11a1f11-14" value="&amp;lt;&amp;lt;literal&amp;gt;&amp;gt;" style="html=1;" vertex="1" parent="4c01e10969289608-1"><mxGeometry x="400" y="403" width="80" height="25" as="geometry"/></mxCell><mxCell id="10abfec4e11a1f11-30" value="" style="endArrow=classic;html=1;" edge="1" parent="4c01e10969289608-1" source="10abfec4e11a1f11-12" target="10abfec4e11a1f11-7"><mxGeometry width="50" height="50" relative="1" as="geometry"><mxPoint x="470" y="310" as="sourcePoint"/><mxPoint x="520" y="260" as="targetPoint"/></mxGeometry></mxCell><mxCell id="10abfec4e11a1f11-31" value="rdf:type" style="text;html=1;resizable=0;;align=center;verticalAlign=middle;labelBackgroundColor=#ffffff;" connectable="0" vertex="1" parent="10abfec4e11a1f11-30"><mxGeometry x="0.1084" y="2" relative="1" as="geometry"><mxPoint as="offset"/></mxGeometry></mxCell><mxCell id="10abfec4e11a1f11-33" value="" style="endArrow=classic;html=1;" edge="1" parent="4c01e10969289608-1" source="10abfec4e11a1f11-12" target="10abfec4e11a1f11-13"><mxGeometry x="613" y="230" width="50" height="50" as="geometry"><mxPoint x="613" y="320" as="sourcePoint"/><mxPoint x="632" y="230" as="targetPoint"/></mxGeometry></mxCell><mxCell id="10abfec4e11a1f11-34" value="rdf:type" style="text;html=1;resizable=0;;align=center;verticalAlign=middle;labelBackgroundColor=#ffffff;" connectable="0" vertex="1" parent="10abfec4e11a1f11-33"><mxGeometry x="0.1084" y="2" relative="1" as="geometry"><mxPoint as="offset"/></mxGeometry></mxCell><mxCell id="10abfec4e11a1f11-38" value="" style="curved=1;endArrow=classic;html=1;" edge="1" parent="4c01e10969289608-1" source="10abfec4e11a1f11-12" target="10abfec4e11a1f11-5"><mxGeometry width="50" height="50" relative="1" as="geometry"><mxPoint x="550" y="400" as="sourcePoint"/><mxPoint x="380" y="250" as="targetPoint"/><Array as="points"><mxPoint x="380" y="300"/></Array></mxGeometry></mxCell><mxCell id="10abfec4e11a1f11-41" value="skos:inScheme" style="text;html=1;resizable=0;;align=center;verticalAlign=middle;labelBackgroundColor=#ffffff;" connectable="0" vertex="1" parent="10abfec4e11a1f11-38"><mxGeometry x="-0.1055" y="-8" relative="1" as="geometry"><mxPoint as="offset"/></mxGeometry></mxCell><mxCell id="10abfec4e11a1f11-39" value="" style="curved=1;endArrow=classic;html=1;" edge="1" parent="4c01e10969289608-1" source="10abfec4e11a1f11-5" target="10abfec4e11a1f11-12"><mxGeometry x="304" y="233" width="50" height="50" as="geometry"><mxPoint x="304" y="233" as="sourcePoint"/><mxPoint x="570" y="328" as="targetPoint"/><Array as="points"><mxPoint x="430" y="233"/></Array></mxGeometry></mxCell><mxCell id="10abfec4e11a1f11-40" value="skos:hasTopConcept" style="text;html=1;resizable=0;;align=center;verticalAlign=middle;labelBackgroundColor=#ffffff;" connectable="0" vertex="1" parent="10abfec4e11a1f11-39"><mxGeometry relative="1" as="geometry"><mxPoint x="30" y="19" as="offset"/></mxGeometry></mxCell><mxCell id="10abfec4e11a1f11-43" value="" style="curved=1;endArrow=classic;html=1;" edge="1" parent="4c01e10969289608-1" source="10abfec4e11a1f11-12" target="10abfec4e11a1f11-12"><mxGeometry x="304" y="233" width="50" height="50" as="geometry"><mxPoint x="570" y="328" as="sourcePoint"/><mxPoint x="610" y="440" as="targetPoint"/><Array as="points"><mxPoint x="563" y="410"/><mxPoint x="490" y="360"/><mxPoint x="540" y="370"/><mxPoint x="670" y="400"/></Array></mxGeometry></mxCell><mxCell id="10abfec4e11a1f11-44" value="skos:broader&lt;div&gt;skos:narrower&lt;/div&gt;" style="text;html=1;resizable=0;;align=center;verticalAlign=middle;labelBackgroundColor=#ffffff;" connectable="0" vertex="1" parent="10abfec4e11a1f11-43"><mxGeometry x="-0.1055" y="-8" relative="1" as="geometry"><mxPoint as="offset"/></mxGeometry></mxCell><mxCell id="10abfec4e11a1f11-47" style="edgeStyle=orthogonalEdgeStyle;rounded=0;html=1;exitX=0.5;exitY=0;entryX=0.5;entryY=0" edge="1" parent="4c01e10969289608-1" source="10abfec4e11a1f11-14" target="10abfec4e11a1f11-14"><mxGeometry relative="1" as="geometry"/></mxCell><mxCell id="10abfec4e11a1f11-48" value="&amp;lt;&amp;lt;literal&amp;gt;&amp;gt;" style="html=1;" vertex="1" parent="4c01e10969289608-1"><mxGeometry x="785" y="198" width="80" height="25" as="geometry"/></mxCell><mxCell id="10abfec4e11a1f11-49" value="" style="endArrow=classic;html=1;" edge="1" parent="4c01e10969289608-1" source="10abfec4e11a1f11-12" target="10abfec4e11a1f11-14"><mxGeometry width="50" height="50" relative="1" as="geometry"><mxPoint x="610" y="510" as="sourcePoint"/><mxPoint x="660" y="460" as="targetPoint"/></mxGeometry></mxCell><mxCell id="10abfec4e11a1f11-50" value="skos:prefLabel&lt;div&gt;rdfs:label&lt;/div&gt;" style="text;html=1;resizable=0;;align=center;verticalAlign=middle;labelBackgroundColor=#ffffff;" connectable="0" vertex="1" parent="10abfec4e11a1f11-49"><mxGeometry x="-0.0738" y="3" relative="1" as="geometry"><mxPoint as="offset"/></mxGeometry></mxCell><mxCell id="10abfec4e11a1f11-51" value="" style="endArrow=classic;html=1;" edge="1" parent="4c01e10969289608-1" source="10abfec4e11a1f11-12" target="10abfec4e11a1f11-48"><mxGeometry x="820" y="220" width="50" height="50" as="geometry"><mxPoint x="937" y="220" as="sourcePoint"/><mxPoint x="820" y="288" as="targetPoint"/></mxGeometry></mxCell><mxCell id="10abfec4e11a1f11-52" value="skos:notation" style="text;html=1;resizable=0;;align=center;verticalAlign=middle;labelBackgroundColor=#ffffff;" connectable="0" vertex="1" parent="10abfec4e11a1f11-51"><mxGeometry x="-0.0738" y="3" relative="1" as="geometry"><mxPoint as="offset"/></mxGeometry></mxCell><mxCell id="10abfec4e11a1f11-53" value="" style="endArrow=classic;html=1;" edge="1" parent="4c01e10969289608-1" source="10abfec4e11a1f11-5" target="10abfec4e11a1f11-55"><mxGeometry x="261" y="80" width="50" height="50" as="geometry"><mxPoint x="261" y="170" as="sourcePoint"/><mxPoint x="280" y="140" as="targetPoint"/></mxGeometry></mxCell><mxCell id="10abfec4e11a1f11-54" value="rdf:type" style="text;html=1;resizable=0;;align=center;verticalAlign=middle;labelBackgroundColor=#ffffff;" connectable="0" vertex="1" parent="10abfec4e11a1f11-53"><mxGeometry x="0.1084" y="2" relative="1" as="geometry"><mxPoint as="offset"/></mxGeometry></mxCell><mxCell id="10abfec4e11a1f11-55" value="skos:ConceptScheme" style="html=1;" vertex="1" parent="4c01e10969289608-1"><mxGeometry x="210" y="310" width="140" height="25" as="geometry"/></mxCell></root></mxGraphModel>